Workbook

Sheet Bloomberg Data
A1: Ticker | B1: Tkr & Exch | C1: Short Name | D1: S&P LT LC | E1: Rating Scale | F1: ABS Rating Scale | G1: Sec Type | H1: Curncy | I1: Net Sales - 5 Yr Geo Gr | J1: Mkt Cap | K1: Tot Assets | L1: Curr Ratio | M1: Cntry Terrtry Of Rsk | N1: Ind Sector | O1: Debt/Assets | P1: 5Yr Avg ROE | Q1: ROE | R1: ROA - 5 Yr Geo Gr | S1: ROA | T1: EBITDA / Iexp | U1: Cash Ratio | V1: Debt/EBITDA | W1: Net Dbt / EBITDA Adj | X1: BEst P/E Nxt Yr | Y1: FCF Margin | Z1: BB 5Y Dflt Prob
A2: NVDA US | B2: NVDA US | C2: NVIDIA CORP | D2: AA | E2: =VLOOKUP($D2,'Rating Lookup'!$A$2:$B$20,2,0) -> 1.56 | F2: =VLOOKUP($D2,'Rating Lookup (2)'!$A$2:$B$20,2,0) -> 1 | G2: Common Stock | H2: USD | I2: 66.898582 | J2: 5118058000000 | K2: 206803 | L2: 3.9052638 | M2: US | N2: Technology | O2: 5.5182952 | P2: 74.977172 | Q2: 114.28807 | R2: 32.039183 | S2: 82.974465 | T2: 516.18533 | U2: 1.9449678 | V2: 0.077171851 | W2: -0.62948222 | X2: 16.160312 | Y2: 44.770258 | Z2: 0.0013131947
A3: 0RIH LN | B3: 0RIH LN | C3: ALPHABET INC-A | D3: AA+ | E3: =VLOOKUP(D3,'Rating Lookup'!$A$2:$B$20,2,0) -> 1.28 | F3: =VLOOKUP($D3,'Rating Lookup (2)'!$A$2:$B$20,2,0) -> 1 | G3: Common Stock | H3: USD | I3: 17.154839 | J3: 4.2199273e+12 | K3: 595281 | L3: 2.0053336 | M3: US | N3: Communications | O3: 10.919213 | P3: 30.331909 | Q3: 49.548547 | R3: 13.329906 | S3: 34.297588 | T3: 208.58696 | U3: 1.2345418 | V3: 0.67248181 | W3: -0.70180689 | X3: 16.068936 | Y3: 18.18755 | Z3: 0.0026449281
A4: MSFT US | B4: MSFT US | C4: MICROSOFT CORP | D4: AAA | E4: =VLOOKUP(D4,'Rating Lookup'!$A$2:$B$20,2,0) -> 1 | F4: =VLOOKUP($D4,'Rating Lookup (2)'!$A$2:$B$20,2,0) -> 1 | G4: Common Stock | H4: USD | I4: 14.571907 | J4: 3.6194336e+12 | K4: 758376 | L4: 1.2303273 | M4: US | N4: Technology | O4: 16.985374 | P4: 38.085611 | Q4: 34.038627 | R4: 0.12982992 | S4: 19.420798 | T4: 65.794494 | U4: 0.45516363 | V4: 0.64169394 | W4: 0.25889339 | X4: 20.750532 | Y4: 20.186597 | Z4: 0.0021255131
A5: AMZN US | B5: AMZN US | C5: AMAZON.COM INC | D5: AA | E5: =VLOOKUP(D5,'Rating Lookup'!$A$2:$B$20,2,0) -> 1.56 | F5: =VLOOKUP($D5,'Rating Lookup (2)'!$A$2:$B$20,2,0) -> 1 | G5: Common Stock | H5: USD | I5: 13.178195 | J5: 2.8152278e+12 | K5: 818042 | L5: 1.0508153 | M5: US | N5: Communications | O5: 20.773261 | P5: 18.19119 | Q5: 30.558338 | R5: 6.6370145 | S5: 15.218417 | T5: 70.244943 | U5: 0.56434027 | V5: 1.313142 | W5: 0.62298523 | X5: 21.135315 | Y5: 1.0733355 | Z5: 0.0055734605
A6: TSM US | B6: TSM US | C6: TAIWAN SEMIC-ADR | D6: AA- | E6: =VLOOKUP(D6,'Rating Lookup'!$A$2:$B$20,2,0) -> 1.83 | F6: =VLOOKUP($D6,'Rating Lookup (2)'!$A$2:$B$20,2,0) -> 1 | G6: ADR | H6: USD | I6: 23.251096 | J6: 2.1571583e+12 | K6: 7933023.9 | L6: 2.6180249 | M6: TW | N6: Technology | O6: 13.419633 | P6: 32.262359 | Q6: 40.624113 | R6: 2.6524117 | S6: 27.311519 | T6: 212.13468 | U6: 2.1045638 | V6: 0.37757228 | W6: -0.86971974 | X6: 18.902192 | Y6: 28.519694 | Z6: 0.0024731531
A7: AVGO US | B7: AVGO US | C7: BROADCOM INC | D7: A- | E7: =VLOOKUP(D7,'Rating Lookup'!$A$2:$B$20,2,0) -> 2.67 | F7: =VLOOKUP($D7,'Rating Lookup (2)'!$A$2:$B$20,2,0) -> 2 | G7: Common Stock | H7: USD | I7: 21.743712 | J7: 1.7046886e+12 | K7: 171092 | L7: 1.7053581 | M7: US | N7: Technology | O7: 38.845183 | P7: 37.27325 | Q7: 37.280721 | R7: 27.183031 | S7: 17.055278 | T7: 10.729283 | U7: 0.87382521 | V7: 1.5640618 | W7: 1.0725808 | X7: 18.594188 | Y7: 42.127506 | Z7: 0.0093230428
A8: META US | B8: META US | C8: META PLATFORMS-A | D8: AA- | E8: =VLOOKUP(D8,'Rating Lookup'!$A$2:$B$20,2,0) -> 1.83 | F8: =VLOOKUP($D8,'Rating Lookup (2)'!$A$2:$B$20,2,0) -> 1 | G8: Common Stock | H8: USD | I8: 18.511415 | J8: 1.4383475e+12 | K8: 366021 | L8: 2.5987666 | M8: US | N8: Communications | O8: 23.244841 | P8: 29.007156 | Q8: 29.848496 | R8: -1.1128224 | S8: 18.288707 | T8: 89.862661 | U8: 1.9502821 | V8: 1.0242759 | W8: 0.19479671 | X8: 14.741775 | Y8: 22.943682 | Z8: 0.007376263
A9: TSLA US | B9: TSLA US | C9: TESLA INC | D9: BBB | E9: =VLOOKUP(D9,'Rating Lookup'!$A$2:$B$20,2,0) -> 3.22 | F9: =VLOOKUP($D9,'Rating Lookup (2)'!$A$2:$B$20,2,0) -> 3 | G9: Common Stock | H9: USD | I9: 24.630713 | J9: 1.3905566e+12 | K9: 137806 | L9: 2.1644069 | M9: US | N9: Consumer, Cyclical | O9: 10.680957 | P9: 19.574177 | Q9: 4.6366006 | R9: 11.85083 | S9: 2.7456684 | T9: 36.298817 | U9: 1.3892603 | V9: 1.4821643 | W9: -2.5399352 | X9: 159.89101 | Y9: 6.5593133 | Z9: 0.0055410065
A10: SMSN LI | B10: SMSN LI | C10: SAMSUN-GDR REG S | D10: AA- | E10: =VLOOKUP(D10,'Rating Lookup'!$A$2:$B$20,2,0) -> 1.83 | F10: =VLOOKUP($D10,'Rating Lookup (2)'!$A$2:$B$20,2,0) -> 1 | G10: GDR | H10: USD | I10: 7.0946687 | J10: 1.0911494e+12 | K10: 566942110 | L10: 2.3276146 | M10: KR | N10: Technology | O10: 4.4518018 | P10: 9.6715081 | Q10: 27.572439 | R10: 2.7692147 | S10: 23.675169 | T10: 149.43906 | U10: 1.1826475 | V10: 0.098115972 | W10: -0.73378957 | X10: 3.6688505 | Y10: 11.328626 | Z10: 0.022897396
A11: MU US | B11: MU US | C11: MICRON TECH | D11: BBB+ | E11: =VLOOKUP(D11,'Rating Lookup'!$A$2:$B$20,2,0) -> 2.94 | F11: =VLOOKUP($D11,'Rating Lookup (2)'!$A$2:$B$20,2,0) -> 3 | G11: Common Stock | H11: USD | I11: 11.763119 | J11: 1.0443555e+12 | K11: 82798 | L11: 2.517985 | M11: US | N11: Technology | O11: 18.541511 | P11: 7.8369761 | Q11: 66.638059 | R11: 16.449274 | S11: 47.498224 | T11: 38.312369 | U11: 0.89986031 | V11: 0.093330991 | W11: -0.34733779 | X11: 6.0965005 | Y11: 4.4625181 | Z11: 0.017337952
A12: WMT US | B12: WMT US | C12: WALMART INC | D12: AA | E12: =VLOOKUP(D12,'Rating Lookup'!$A$2:$B$20,2,0) -> 1.56 | F12: =VLOOKUP($D12,'Rating Lookup (2)'!$A$2:$B$20,2,0) -> 1 | G12: Common Stock | H12: USD | I12: 4.986133 | J12: 8.3265382e+11 | K12: 284668 | L12: 0.78975332 | M12: US | N12: Consumer, Cyclical | O12: 23.569562 | P12: 19.156154 | Q12: 23.441714 | R12: 7.7538114 | S12: 7.8179587 | T12: 20.044003 | U12: 0.09981483 | V12: 1.5568995 | W12: 1.2955899 | X12: 32.383163 | Y12: 2.092509 | Z12: 0.0025529327
A13: AMD US | B13: AMD US | C13: ADV MICRO DEVICE | D13: A | E13: =VLOOKUP(D13,'Rating Lookup'!$A$2:$B$20,2,0) -> 2.39 | F13: =VLOOKUP($D13,'Rating Lookup (2)'!$A$2:$B$20,2,0) -> 2 | G13: Common Stock | H13: USD | I13: 28.823891 | J13: 7.7384198e+11 | K13: 76926 | L13: 2.8500264 | M13: US | N13: Technology | O13: 5.00091 | P13: 12.659237 | Q13: 10.141147 | R13: -29.14715 | S13: 8.078652 | T13: 52.625954 | U13: 1.1160233 | V13: 0.44939569 | W13: -0.90951204 | X13: 31.008694 | Y13: 19.443402 | Z13: 0.011599008
A14: TCTZF US | B14: TCTZF US | C14: TENCENT | D14: A+ | E14: =VLOOKUP(D14,'Rating Lookup'!$A$2:$B$20,2,0) -> 2.11 | F14: =VLOOKUP($D14,'Rating Lookup (2)'!$A$2:$B$20,2,0) -> 2 | G14: Common Stock | H14: USD | I14: 9.2938176 | J14: 5.1629308e+11 | K14: 2038986 | L14: 1.4426616 | M14: CN | N14: Communications | O14: 19.931427 | P14: 22.478385 | Q14: 20.929468 | R14: -3.3746254 | S14: 11.288028 | T14: 22.858948 | U14: 1.0339236 | V14: 1.4293747 | W14: 0.029909662 | X14: 12.248491 | Y14: 29.719886 | Z14: 0.01041125
... A655: HLNFF US | B655: HLNFF US | C655: HIGH LINER FOODS | D655: B+ | E655: =VLOOKUP(D655,'Rating Lookup'!$A$2:$B$20,2,0) -> 4.61 | F655: =VLOOKUP($D655,'Rating Lookup (2)'!$A$2:$B$20,2,0) -> 5 | G655: Common Stock | H655: USD | I655: 4.4135542 | J655: 3.0708741e+08 | K655: 963.957 | L655: 2.1807025 | M655: CA | N655: Consumer, Non-cyclical | O655: 30.924408 | P655: 12.315206 | Q655: 6.2583783 | R655: 2.2541504 | S655: 2.7737041 | T655: 3.4298699 | U655: 0.0022052199 | V655: 3.5297604 | W655: 3.1446819 | X655: 7.4595238 | Y655: -0.74983031 | Z655: 0.013153189

Sheet Rating Lookup
A1: Rating | B1: Numeric Score (1=AAA, 6=C)
A2: AAA | B2: 1
A3: AA+ | B3: 1.28 | C3: =B3-B2 -> 0.28
A4: AA | B4: 1.56 | C4: =B4-B3 -> 0.28
A5: AA- | B5: 1.83 | C5: =B5-B4 -> 0.27
A6: A+ | B6: 2.11 | C6: =B6-B5 -> 0.28
A7: A | B7: 2.39 | C7: =B7-B6 -> 0.28
A8: A- | B8: 2.67 | C8: =B8-B7 -> 0.28
A9: BBB+ | B9: 2.94 | C9: =B9-B8 -> 0.27
A10: BBB | B10: 3.22 | C10: =B10-B9 -> 0.28
A11: BBB- | B11: 3.5 | C11: =B11-B10 -> 0.28
A12: BB+ | B12: 3.78 | C12: =B12-B11 -> 0.28
A13: BB | B13: 4.06 | C13: =B13-B12 -> 0.28
A14: BB- | B14: 4.33 | C14: =B14-B13 -> 0.27
... A20: C | B20: 6 | C20: =B20-B19 -> 0.28

Sheet Example VLOOKUP
A1: Your Rating | B1: Numeric Score (VLOOKUP)
A2: AAA | B2: =VLOOKUP(A2,'Rating Lookup'!$A$2:$B$20,2,FALSE()) -> 1
A3: AA- | B3: =VLOOKUP(A3,'Rating Lookup'!$A$2:$B$20,2,FALSE()) -> 1.83
A4: A- | B4: =VLOOKUP(A4,'Rating Lookup'!$A$2:$B$20,2,FALSE()) -> 2.67
A5: BB | B5: =VLOOKUP(A5,'Rating Lookup'!$A$2:$B$20,2,FALSE()) -> 4.06
A6: CCC | B6: =VLOOKUP(A6,'Rating Lookup'!$A$2:$B$20,2,FALSE()) -> 5.44
A7: C | B7: =VLOOKUP(A7,'Rating Lookup'!$A$2:$B$20,2,FALSE()) -> 6
A9: Formula used: =VLOOKUP(A2,'Rating Lookup'!$A$2:$B$20,2,FALSE)
A10: Scale: 19 notches from AAA to C evenly spaced between 1.00 and 6.00 (step = 0.2778).

Sheet Rating Lookup (2)
A1: Rating | B1: Tier | C1: Tier Label
A2: AAA | B2: 1 | C2: Prime / High Grade
A3: AA+ | B3: 1 | C3: Prime / High Grade
A4: AA | B4: 1 | C4: Prime / High Grade
A5: AA- | B5: 1 | C5: Prime / High Grade
A6: A+ | B6: 2 | C6: Upper Medium Grade
A7: A | B7: 2 | C7: Upper Medium Grade
A8: A- | B8: 2 | C8: Upper Medium Grade
A9: BBB+ | B9: 3 | C9: Lower Medium Grade
A10: BBB | B10: 3 | C10: Lower Medium Grade
A11: BBB- | B11: 3 | C11: Lower Medium Grade
A12: BB+ | B12: 4 | C12: Speculative
A13: BB | B13: 4 | C13: Speculative
... A20: C | B20: 6 | C20: Substantial Risk / Default Watch

Sheet Example VLOOKUP (2)
A1: Your Rating | B1: Tier (VLOOKUP result)
A2: AAA | B2: =VLOOKUP(A2,'Rating Lookup (2)'!$A$2:$C$20,2,FALSE()) -> 1
A3: AA- | B3: =VLOOKUP(A3,'Rating Lookup (2)'!$A$2:$C$20,2,FALSE()) -> 1
A4: A- | B4: =VLOOKUP(A4,'Rating Lookup (2)'!$A$2:$C$20,2,FALSE()) -> 2
A5: BB | B5: =VLOOKUP(A5,'Rating Lookup (2)'!$A$2:$C$20,2,FALSE()) -> 4
A6: CCC | B6: =VLOOKUP(A6,'Rating Lookup (2)'!$A$2:$C$20,2,FALSE()) -> 6
A7: Formula used: =VLOOKUP(A2,'Rating Lookup'!$A$2:$C$20,2,FALSE)
